<krpano version="1.19" onstart="loadpano(%FIRSTXML%/scene/k_3708042259/scene.xml,null,MERGE);ini();playtourbksound();" googlemap="false" idletime="" isautoplay="false" basedir="%FIRSTXML%" bgcolor="0xffffff" actionintervalbase="frame" colorcorrection="default" logkey="false" showerrors="false" istransition="false">
  <include url="%FIRSTXML%/public/publicexml.xml" />
  <display fps="60" details="28" tessmode="-1" movequality="HIGH" stillquality="HIGH" stilltime="0.25" flash10="on" />
  <action name="playtourbksound">if(soundinterface.mute== false, set(soundinterface.mute,true);, set(soundinterface.mute,false););playsound(tourbksound,%SWFPATH%/sound/amingpin.mp3,0);</action>
  <events onmousedown="" onmouseup="" onxmlcomplete="" onloadcomplete="" onidle="" onresize="" />
  <skin id="1021" url="skin/skin21/skins.xml" thumb_width="60" thumb_height="60" interval="10" showtype="0" object_name="萧山铭品 大名城6-1-401" scene_num="12" delhot="0" vrshow="zssys" zs_vr="true" zs_gro="true" zs_contact="true" zs_autorate="false" zs_share="true" zs_sound="ture" zs_shapan="true" zs_dianzan="true" dz_count="0" openmarquee="true" marqueetext="大名城61401。项目经理：刘长军 设计师：刘晶 监理：孔国祥" object_number="h32021082215041957662786" website="http://www.mpzs.net" showmenu="false" />
  <plugin name="zfblogo" url="%SWFPATH%/plugins/logo.png" keep="true" capture="true" x="3" y="5" width="" height="" visible="true" enabled="true" handcursor="true" children="true" zorder="99" alpha="1" blendmode="normal" smoothing="true" scale="0.6" align="lefttop" edge="lefttop" ox="" oy="" rotate="0" parent="" background="" border="false" borderwidth="" blur="" textblur="" glow="" glowcolor="" textshadow="" autosize="" onclick="openurl(https://www.86pano.com,_blank);" onloaded="" type="plugin_p" roundedge="5" devices="all" />
  <layer name="shop_title" url="%SWFPATH%/plugins/textfield.swf" align="leftbottom" edge="leftbottom" x="0" y="-23" zorder="4" width="190" enabled="true" background="false" border="false" css="text-align:left; color:#ffffff;font-family:宋体; font-size:11px;width;190px;overflow:hidden;" textshadow="1" visible="true" onautosized="" keep="true" parent="plugin[zfblogo]" html="" />
  <layer name="type_time" url="%SWFPATH%/plugins/textfield.swf" align="leftbottom" edge="leftbottom" x="0" y="-40" zorder="4" width="190" enabled="true" background="false" border="false" css="text-align:left; color:#ffffff;font-family:宋体; font-size:11px;width;190px;overflow:hidden;" textshadow="1" visible="true" onautosized="" keep="true" parent="plugin[zfblogo]" html="" />
  <layer name="renqi" url="%SWFPATH%/plugins/textfield.swf" align="leftbottom" edge="leftbottom" x="0" y="-57" zorder="4" width="190" enabled="true" background="false" border="false" css="text-align:left; color:#ffffff;font-family:宋体; font-size:11px;width;190px;overflow:hidden;" textshadow="1" visible="false" onautosized="" keep="true" parent="plugin[zfblogo]" html="" />
  <plugin name="transitionplugin" url="%SWFPATH%/plugins/videoplayer.swf" alturl="%SWFPATH%/plugins/videoplayer.js" videourl="" width="100%" height="100%" altvideourl="" posterurl="" align="center" x="0" y="0" pausedonstart="false" loop="false" volume="1.0" keetp="true" buffertime="0.1" updateeveryframe="true" onvideoready="" onvideopaused="" onvideocomplete="" onunsupported="" visible="true" zorder="10000" onloaded="" enabled="false" />
  <plugin name="touchAlert" url="%SWFPATH%/plugins/touchAlert.png" keep="true" capture="true" x="0" y="0" width="" height="" visible="true" enabled="true" handcursor="true" children="true" zorder="1000000" alpha="1" blendmode="normal" smoothing="true" scale="0.6" align="center" edge="center" ox="" oy="" rotate="0" parent="" background="" border="false" borderwidth="" blur="" textblur="" glow="" glowcolor="" textshadow="" autosize="" onclick="removeplugin(touchAlert);" onloaded="delayedcall(3,removeplugin(touchAlert));" type="plugin_p" alturl="%SWFPATH%/plugins/touchAlert.png" roundedge="5" devices="all" />
  <hotspot name="bottomlogo" url="%SWFPATH%/plugins/botlogo.png" keep="true" capture="true" ath="-33.65092083338052" atv="90" zoom="true" distorted="false" width="550" height="550" visible="true" enabled="false" handcursor="true" children="true" zorder="0" alpha="1" blendmode="normal" smoothing="true" refreshrate="auto" onhover="" onclick="" details="8" flying="0" inverserotation="false" usecontentsize="false" rx="0.0" ry="0.0" rz="0.0" type="hotspot" scale="0.5" backup_rx="0" backup_ry="0" onunsupported="" altonloaded="" isonload="" isonclick="" range="90" s_ath="0" s_atv="0" s_fov="90" style="" devices="all" twidth="80" />
  <autorotate enabled="true" waittime="1.5" speed="10" tofov="off" />
  <data name="infocontent" title="infocontent"><![CDATA[]]></data>
  <scenes name="k_1431156938" scene_name="厨房" isobjectscene="true" isgoogle="false" ispluginmap="false" scene_xml="scene/k_1431156938/scene.xml" type="scene" onstart="action(loadpano,scene/k_1431156938/scene.xml);" scenetype="sphere" type_id="1001" pstime="202108221449" />
  <scenes name="k_2207517222" scene_name="玄关" isobjectscene="true" isgoogle="false" ispluginmap="false" scene_xml="scene/k_2207517222/scene.xml" type="scene" onstart="action(loadpano,scene/k_2207517222/scene.xml);" scenetype="sphere" type_id="1001" pstime="202108221449" />
  <scenes name="k_3708042259" scene_name="客餐厅" isobjectscene="true" isgoogle="false" ispluginmap="false" scene_xml="scene/k_3708042259/scene.xml" type="scene" onstart="action(loadpano,scene/k_3708042259/scene.xml);" scenetype="sphere" type_id="1001" pstime="202108221449" />
  <scenes name="k_4243887374" scene_name="阳台" isobjectscene="true" isgoogle="false" ispluginmap="false" scene_xml="scene/k_4243887374/scene.xml" type="scene" onstart="action(loadpano,scene/k_4243887374/scene.xml);" scenetype="sphere" type_id="1001" pstime="202108221450" />
  <scenes name="k_552012652" scene_name="走廊" isobjectscene="true" isgoogle="false" ispluginmap="false" scene_xml="scene/k_552012652/scene.xml" type="scene" onstart="action(loadpano,scene/k_552012652/scene.xml);" scenetype="sphere" type_id="1001" pstime="202108221450" />
  <scenes name="k_61807433815" scene_name="次卧2" isobjectscene="true" isgoogle="false" ispluginmap="false" scene_xml="scene/k_61807433815/scene.xml" type="scene" onstart="action(loadpano,scene/k_61807433815/scene.xml);" scenetype="sphere" type_id="1001" pstime="202108221451" />
  <scenes name="k_71507029912" scene_name="主卧" isobjectscene="true" isgoogle="false" ispluginmap="false" scene_xml="scene/k_71507029912/scene.xml" type="scene" onstart="action(loadpano,scene/k_71507029912/scene.xml);" scenetype="sphere" type_id="1001" pstime="202108221451" />
  <scenes name="k_81380547477" scene_name="主卫" isobjectscene="true" isgoogle="false" ispluginmap="false" scene_xml="scene/k_81380547477/scene.xml" type="scene" onstart="action(loadpano,scene/k_81380547477/scene.xml);" scenetype="sphere" type_id="1001" pstime="202108221451" />
  <scenes name="k_91007741335" scene_name="书房" isobjectscene="true" isgoogle="false" ispluginmap="false" scene_xml="scene/k_91007741335/scene.xml" type="scene" onstart="action(loadpano,scene/k_91007741335/scene.xml);" scenetype="sphere" type_id="1001" pstime="202108221452" />
  <scenes name="k_10924394896" scene_name="次卫" isobjectscene="true" isgoogle="false" ispluginmap="false" scene_xml="scene/k_10924394896/scene.xml" type="scene" onstart="action(loadpano,scene/k_10924394896/scene.xml);" scenetype="sphere" type_id="1001" pstime="202108221452" />
  <scenes name="k_111357354518" scene_name="盥洗间" isobjectscene="true" isgoogle="false" ispluginmap="false" scene_xml="scene/k_111357354518/scene.xml" type="scene" onstart="action(loadpano,scene/k_111357354518/scene.xml);" scenetype="sphere" type_id="1001" pstime="202108221452" />
  <scenes name="k_122088859996" scene_name="次卧" isobjectscene="true" isgoogle="false" ispluginmap="false" scene_xml="scene/k_122088859996/scene.xml" type="scene" onstart="action(loadpano,scene/k_122088859996/scene.xml);" scenetype="sphere" type_id="1001" pstime="202108221450" />
</krpano>